asgi_runserver/__init__.py
asgi_runserver/management/__init__.py
asgi_runserver/management/commands/__init__.py
asgi_runserver/management/commands/runserver.py
asgi_runserver-0.1.3.dist-info/WHEEL
asgi_runserver-0.1.3.dist-info/METADATA
asgi_runserver-0.1.3.dist-info/RECORD
