Metadata-Version: 2.1
Name: asgi-runserver
Version: 0.1.3
Summary: 
Author: Joshua Massover
Author-email: massover@simplebet.io
Requires-Python: >=3.7,<4.0
Classifier: Programming Language :: Python :: 3
Classifier: Programming Language :: Python :: 3.7
Classifier: Programming Language :: Python :: 3.8
Requires-Dist: daphne (>=2.5.0,<3.0.0)
Requires-Dist: django (>=3.0.6,<4.0.0)
